zmkj_rknn_tools/__init__.py
zmkj_rknn_tools/cli.py
zmkj_rknn_tools/config.py
zmkj_rknn_tools/converter.py
zmkj_rknn_tools/data.py
zmkj_rknn_tools/detector.py
zmkj_rknn_tools/postprocess.py
zmkj_rknn_tools/py.typed
zmkj_rknn_tools/visualize.py
zmkj_rknn_tools/examples/README.md
zmkj_rknn_tools/examples/image_inference.py
zmkj_rknn_tools/examples/img.py
zmkj_rknn_tools/examples/model_conversion.py
zmkj_rknn_tools/examples/verify_environment.py
zmkj_rknn_tools/examples/video_inference.py
zmkj_rknn_tools-0.1.1.dist-info/licenses/LICENSE
zmkj_rknn_tools-0.1.1.dist-info/METADATA
zmkj_rknn_tools-0.1.1.dist-info/WHEEL
zmkj_rknn_tools-0.1.1.dist-info/entry_points.txt
zmkj_rknn_tools-0.1.1.dist-info/top_level.txt
zmkj_rknn_tools-0.1.1.dist-info/RECORD
