Metadata-Version: 2.4
Name: zmkj-rknn-tools
Version: 0.1.1
Summary: 瑞芯微端侧的辅助快速验证工具
Author-email: 壹世朱名 <nx740@qq.com>
Maintainer-email: 壹世朱名 <nx740@qq.com>
License: MIT
Project-URL: Homepage, https://github.com/xuntee/rknn-tools
Project-URL: Repository, https://github.com/xuntee/rknn-tools
Project-URL: Documentation, https://github.com/xuntee/rknn-tools#readme
Project-URL: Bug Tracker, https://github.com/xuntee/rknn-tools/issues
Project-URL: Changelog, https://github.com/xuntee/rknn-tools/blob/main/CHANGELOG.md
Keywords: rknn,rockchip,yolov8,object detection,edge computing
Classifier: Development Status :: 4 - Beta
Classifier: Intended Audience :: Developers
Classifier: License :: OSI Approved :: MIT License
Classifier: Operating System :: OS Independent
Classifier: Programming Language :: Python :: 3
Classifier: Programming Language :: Python :: 3.8
Classifier: Programming Language :: Python :: 3.9
Classifier: Programming Language :: Python :: 3.10
Classifier: Programming Language :: Python :: 3.11
Classifier: Programming Language :: Python :: 3.12
Classifier: Topic :: Scientific/Engineering :: Artificial Intelligence
Classifier: Topic :: Software Development :: Libraries :: Python Modules
Requires-Python: >=3.8
License-File: LICENSE
Requires-Dist: numpy>=1.20.0
Requires-Dist: opencv-python>=4.5.0
Requires-Dist: pillow>=8.0.0
Requires-Dist: tqdm>=4.60.0
Provides-Extra: rknn
Requires-Dist: rknn-toolkit2>=1.4.0; extra == "rknn"
Requires-Dist: rknn-toolkit-lite2>=1.4.0; extra == "rknn"
Provides-Extra: yolo
Requires-Dist: zmkj-rknn-yolov8>=0.1.0; extra == "yolo"
Requires-Dist: ultralytics>=8.0.0; extra == "yolo"
Provides-Extra: viz
Requires-Dist: supervision>=0.15.0; extra == "viz"
Requires-Dist: matplotlib>=3.5.0; extra == "viz"
Provides-Extra: dev
Requires-Dist: pytest>=7.0.0; extra == "dev"
Requires-Dist: pytest-cov>=4.0.0; extra == "dev"
Requires-Dist: black>=22.0.0; extra == "dev"
Requires-Dist: isort>=5.10.0; extra == "dev"
Requires-Dist: flake8>=5.0.0; extra == "dev"
Requires-Dist: mypy>=1.0.0; extra == "dev"
Requires-Dist: pre-commit>=2.20.0; extra == "dev"
Provides-Extra: docs
Requires-Dist: sphinx>=5.0.0; extra == "docs"
Requires-Dist: sphinx-rtd-theme>=1.0.0; extra == "docs"
Requires-Dist: myst-parser>=0.18.0; extra == "docs"
Provides-Extra: examples-data
Requires-Dist: zmkj-rknn-examples-data>=0.1.0; extra == "examples-data"
Provides-Extra: all
Requires-Dist: zmkj-rknn-tools[rknn,viz,yolo]; extra == "all"
Provides-Extra: full
Requires-Dist: zmkj-rknn-tools[all,dev,docs,examples-data]; extra == "full"
Dynamic: license-file
